koffie/__init__.py
koffie/_koffie.cpython-37m-darwin.so
koffie-0.1.0.dist-info/LICENSE
koffie-0.1.0.dist-info/METADATA
koffie-0.1.0.dist-info/WHEEL
koffie-0.1.0.dist-info/top_level.txt
koffie-0.1.0.dist-info/RECORD
