Metadata-Version: 2.1
Name: koffie
Version: 0.1.0
Summary: Lightweight and minimalist framework for python web app
Home-page: UNKNOWN
License: UNKNOWN
Platform: UNKNOWN
Requires-Dist: cython
